intermittent_forecast/__init__.py
intermittent_forecast/aggregators/__init__.py
intermittent_forecast/aggregators/adida.py
intermittent_forecast/core/__init__.py
intermittent_forecast/core/_types.py
intermittent_forecast/core/error_metrics.py
intermittent_forecast/core/utils.py
intermittent_forecast/forecasters/__init__.py
intermittent_forecast/forecasters/_base_forecaster.py
intermittent_forecast/forecasters/croston.py
intermittent_forecast/forecasters/double_exponential_smoothing.py
intermittent_forecast/forecasters/simple_exponential_smoothing.py
intermittent_forecast/forecasters/triple_exponential_smoothing.py
intermittent_forecast-1.0.0.dist-info/LICENSE
intermittent_forecast-1.0.0.dist-info/METADATA
intermittent_forecast-1.0.0.dist-info/WHEEL
intermittent_forecast-1.0.0.dist-info/RECORD
