Metadata-Version: 2.3
Name: intermittent-forecast
Version: 1.0.0
Summary: Tools for forecasting intermittent time series
License: MIT
Author: Paul Morgan
Requires-Python: >=3.10,<4.0
Classifier: License :: OSI Approved :: MIT License
Classifier: Programming Language :: Python :: 3
Classifier: Programming Language :: Python :: 3.10
Classifier: Programming Language :: Python :: 3.11
Classifier: Programming Language :: Python :: 3.12
Classifier: Programming Language :: Python :: 3.13
Requires-Dist: numpy (>=1.24)
Requires-Dist: scipy (>=1.11)
